Software/Verilog_FPGA_IceBreaker/PMOD_1414/pmod_1414.v

module pmod_1414 (
	input CLK,      //-- 12 Mhz
	output LEDG_N,  
	output LEDR_N,
	output LED1,
	output LED2,
	output LED3,
	output LED4,
	output LED5,


	output HPDL_D0,
	output HPDL_D1,
	output HPDL_D2,
	output HPDL_D3,
	output HPDL_D4,
	output HPDL_D5,
	output HPDL_D6,

	output HPDL_A0,
	output HPDL_A1,

	output HPDL_WR1,
	output HPDL_WR2,
	output HPDL_WR3,
	output HPDL_WR4

);

  //-- Toggle the green LED
//   assign LEDG_N = counter[23];
  assign LEDG_N = 1'b1; 
 //-- Turn off the other LEDs
  assign LEDR_N = 1'b1;
  assign {LED5, LED4, LED3, LED2, LED1} = 5'b0;
  
  assign HPDL_D6 = data[6];
  assign HPDL_D5 = data[5];
  assign HPDL_D4 = data[4];
  assign HPDL_D3 = data[3];
  assign HPDL_D2 = data[2];
  assign HPDL_D1 = data[1];
  assign HPDL_D0 = data[0];

  reg [23:0] counter = 0;
  reg [3:0] address_counter = 0;
  wire [7:0] data; 
  wire hpdl_clk; 

  // Generate slower clock for display modules 
  always @(posedge CLK) 
    counter <= counter + 1;

 assign hpdl_clk = counter[10];
//   assign hpdl_clk = CLK;

  // Count 0 to 15 for 16 display places
  always @(posedge hpdl_clk) 
	address_counter <= address_counter + 1;

  memory mem_strorage(
          .clk(CLK),
          .w_en(1'b0),
          .r_en(1'b1),
          .w_addr(4'h0),
          .w_data(8'h0),
          .r_addr(address_counter),
          .r_data(data)
      );
  
  // Set address lines 
  assign HPDL_A0 = !address_counter[0];
  assign HPDL_A1 = !address_counter[1];
   
  // Generate write signal for each data and address combination 
  assign  HPDL_WR1 = (address_counter[3] == 0 && address_counter[2] == 0 ) ? hpdl_clk : 1'b1; 
  assign  HPDL_WR2 = (address_counter[3] == 0 && address_counter[2] == 1 ) ? hpdl_clk : 1'b1;
  assign  HPDL_WR3 = (address_counter[3] == 1 && address_counter[2] == 0 ) ? hpdl_clk : 1'b1;
  assign  HPDL_WR4 = (address_counter[3] == 1 && address_counter[2] == 1 ) ? hpdl_clk : 1'b1;

endmodule


//  Memory block for display buffer 
module memory #(
      parameter INIT_FILE = "mem_init.txt"
  )(
      input clk,
      input w_en,
      input r_en,
      input [3:0] w_addr,
      input [3:0] r_addr,
      input [7:0] w_data, 

      output reg [7:0] r_data
  );

      reg [7:0]  mem [0:15];

      always @(posedge clk) begin
          if (w_en == 1'b1) begin
              mem[w_addr] <= w_data;    
          end
          
          if (r_en == 1'b1) begin
              r_data <= mem[r_addr];
          end
      end

      initial if (INIT_FILE) begin
          $readmemh(INIT_FILE, mem);
      end
    
endmodule

Software/Verilog_FPGA_IceBreaker/PMOD_1414/pmod_1414_tb.v
`timescale 1ns/1ps
`define DUMPSTR(x) `"x.vcd`"
module pmod_1414_tb();

parameter DURATION  = 10000;

reg CLK = 0;


always begin
    #41.667
    CLK =!CLK;
end

pmod_1414 UUT(
    .CLK(CLK)

);

initial begin

  $dumpfile(`DUMPSTR(`VCD_OUTPUT));
  $dumpvars(0, pmod_1414_tb);

   #(DURATION) 
  $display("End of simulation");
  $finish;
end

endmodule

Software/Verilog_FPGA_IceBreaker/PMOD_1414/pmod_1414_tb.vcd
$date
	Sat Jan 04 22:19:08 2025
$end
$version
	Icarus Verilog
$end
$timescale
	1ps
$end
$scope module pmod_1414_tb $end
$var parameter 32 ! DURATION $end
$var reg 1 " CLK $end
$scope module UUT $end
$var wire 1 " CLK $end
$var wire 1 # LEDG_N $end
$var wire 1 $ LEDR_N $end
$var wire 1 % hpdl_clk $end
$var wire 8 & data [7:0] $end
$var wire 1 ' LED5 $end
$var wire 1 ( LED4 $end
$var wire 1 ) LED3 $end
$var wire 1 * LED2 $end
$var wire 1 + LED1 $end
$var wire 1 , HPDL_WR4 $end
$var wire 1 - HPDL_WR3 $end
$var wire 1 . HPDL_WR2 $end
$var wire 1 / HPDL_WR1 $end
$var wire 1 0 HPDL_D6 $end
$var wire 1 1 HPDL_D5 $end
$var wire 1 2 HPDL_D4 $end
$var wire 1 3 HPDL_D3 $end
$var wire 1 4 HPDL_D2 $end
$var wire 1 5 HPDL_D1 $end
$var wire 1 6 HPDL_D0 $end
$var wire 1 7 HPDL_A1 $end
$var wire 1 8 HPDL_A0 $end
$var reg 4 9 address_counter [3:0] $end
$var reg 24 : counter [23:0] $end
$scope module mem_strorage $end
$var wire 1 " clk $end
$var wire 4 ; r_addr [3:0] $end
$var wire 1 < r_en $end
$var wire 4 = w_addr [3:0] $end
$var wire 8 > w_data [7:0] $end
$var wire 1 ? w_en $end
$var parameter 96 @ INIT_FILE $end
$var reg 8 A r_data [7:0] $end
$upscope $end
$upscope $end
$upscope $end
$enddefinitions $end
$comment Show the parameter values. $end
$dumpall
b11011010110010101101101010111110110100101101110011010010111010000101110011101000111100001110100 @
b10011100010000 !
$end
#0
$dumpvars
bx A
0?
b0 >
b0 =
1<
b0 ;
b0 :
b0 9
18
17
x6
x5
x4
x3
x2
x1
x0
0/
1.
1-
1,
0+
0*
0)
0(
0'
bx &
0%
1$
1#
0"
$end
#41667
16
05
04
13
02
01
10
b1001001 &
b1001001 A
b1 :
1"
#83334
0"
#125001
b10 :
1"
#166668
0"
#208335
b11 :
1"
#250002
0"
#291669
b100 :
1"
#333336
0"
#375003
b101 :
1"
#416670
0"
#458337
b110 :
1"
#500004
0"
#541671
b111 :
1"
#583338
0"
#625005
b1000 :
1"
#666672
0"
#708339
b1001 :
1"
#750006
0"
#791673
b1010 :
1"
#833340
0"
#875007
b1011 :
1"
#916674
0"
#958341
b1100 :
1"
#1000008
0"
#1041675
b1101 :
1"
#1083342
0"
#1125009
b1110 :
1"
#1166676
0"
#1208343
b1111 :
1"
#1250010
0"
#1291677
b10000 :
1"
#1333344
0"
#1375011
b10001 :
1"
#1416678
0"
#1458345
b10010 :
1"
#1500012
0"
#1541679
b10011 :
1"
#1583346
0"
#1625013
b10100 :
1"
#1666680
0"
#1708347
b10101 :
1"
#1750014
0"
#1791681
b10110 :
1"
#1833348
0"
#1875015
b10111 :
1"
#1916682
0"
#1958349
b11000 :
1"
#2000016
0"
#2041683
b11001 :
1"
#2083350
0"
#2125017
b11010 :
1"
#2166684
0"
#2208351
b11011 :
1"
#2250018
0"
#2291685
b11100 :
1"
#2333352
0"
#2375019
b11101 :
1"
#2416686
0"
#2458353
b11110 :
1"
#2500020
0"
#2541687
b11111 :
1"
#2583354
0"
#2625021
b100000 :
1"
#2666688
0"
#2708355
b100001 :
1"
#2750022
0"
#2791689
b100010 :
1"
#2833356
0"
#2875023
b100011 :
1"
#2916690
0"
#2958357
b100100 :
1"
#3000024
0"
#3041691
b100101 :
1"
#3083358
0"
#3125025
b100110 :
1"
#3166692
0"
#3208359
b100111 :
1"
#3250026
0"
#3291693
b101000 :
1"
#3333360
0"
#3375027
b101001 :
1"
#3416694
0"
#3458361
b101010 :
1"
#3500028
0"
#3541695
b101011 :
1"
#3583362
0"
#3625029
b101100 :
1"
#3666696
0"
#3708363
b101101 :
1"
#3750030
0"
#3791697
b101110 :
1"
#3833364
0"
#3875031
b101111 :
1"
#3916698
0"
#3958365
b110000 :
1"
#4000032
0"
#4041699
b110001 :
1"
#4083366
0"
#4125033
b110010 :
1"
#4166700
0"
#4208367
b110011 :
1"
#4250034
0"
#4291701
b110100 :
1"
#4333368
0"
#4375035
b110101 :
1"
#4416702
0"
#4458369
b110110 :
1"
#4500036
0"
#4541703
b110111 :
1"
#4583370
0"
#4625037
b111000 :
1"
#4666704
0"
#4708371
b111001 :
1"
#4750038
0"
#4791705
b111010 :
1"
#4833372
0"
#4875039
b111011 :
1"
#4916706
0"
#4958373
b111100 :
1"
#5000040
0"
#5041707
b111101 :
1"
#5083374
0"
#5125041
b111110 :
1"
#5166708
0"
#5208375
b111111 :
1"
#5250042
0"
#5291709
b1000000 :
1"
#5333376
0"
#5375043
b1000001 :
1"
#5416710
0"
#5458377
b1000010 :
1"
#5500044
0"
#5541711
b1000011 :
1"
#5583378
0"
#5625045
b1000100 :
1"
#5666712
0"
#5708379
b1000101 :
1"
#5750046
0"
#5791713
b1000110 :
1"
#5833380
0"
#5875047
b1000111 :
1"
#5916714
0"
#5958381
b1001000 :
1"
#6000048
0"
#6041715
b1001001 :
1"
#6083382
0"
#6125049
b1001010 :
1"
#6166716
0"
#6208383
b1001011 :
1"
#6250050
0"
#6291717
b1001100 :
1"
#6333384
0"
#6375051
b1001101 :
1"
#6416718
0"
#6458385
b1001110 :
1"
#6500052
0"
#6541719
b1001111 :
1"
#6583386
0"
#6625053
b1010000 :
1"
#6666720
0"
#6708387
b1010001 :
1"
#6750054
0"
#6791721
b1010010 :
1"
#6833388
0"
#6875055
b1010011 :
1"
#6916722
0"
#6958389
b1010100 :
1"
#7000056
0"
#7041723
b1010101 :
1"
#7083390
0"
#7125057
b1010110 :
1"
#7166724
0"
#7208391
b1010111 :
1"
#7250058
0"
#7291725
b1011000 :
1"
#7333392
0"
#7375059
b1011001 :
1"
#7416726
0"
#7458393
b1011010 :
1"
#7500060
0"
#7541727
b1011011 :
1"
#7583394
0"
#7625061
b1011100 :
1"
#7666728
0"
#7708395
b1011101 :
1"
#7750062
0"
#7791729
b1011110 :
1"
#7833396
0"
#7875063
b1011111 :
1"
#7916730
0"
#7958397
b1100000 :
1"
#8000064
0"
#8041731
b1100001 :
1"
#8083398
0"
#8125065
b1100010 :
1"
#8166732
0"
#8208399
b1100011 :
1"
#8250066
0"
#8291733
b1100100 :
1"
#8333400
0"
#8375067
b1100101 :
1"
#8416734
0"
#8458401
b1100110 :
1"
#8500068
0"
#8541735
b1100111 :
1"
#8583402
0"
#8625069
b1101000 :
1"
#8666736
0"
#8708403
b1101001 :
1"
#8750070
0"
#8791737
b1101010 :
1"
#8833404
0"
#8875071
b1101011 :
1"
#8916738
0"
#8958405
b1101100 :
1"
#9000072
0"
#9041739
b1101101 :
1"
#9083406
0"
#9125073
b1101110 :
1"
#9166740
0"
#9208407
b1101111 :
1"
#9250074
0"
#9291741
b1110000 :
1"
#9333408
0"
#9375075
b1110001 :
1"
#9416742
0"
#9458409
b1110010 :
1"
#9500076
0"
#9541743
b1110011 :
1"
#9583410
0"
#9625077
b1110100 :
1"
#9666744
0"
#9708411
b1110101 :
1"
#9750078
0"
#9791745
b1110110 :
1"
#9833412
0"
#9875079
b1110111 :
1"
#9916746
0"
#9958413
b1111000 :
1"
